wellpapp/__init__.py
wellpapp/__main__.py
wellpapp/_util.py
wellpapp/client.py
wellpapp/util.py
wellpapp/vt.py
wellpapp/shell/__init__.py
wellpapp/shell/add.py
wellpapp/shell/export.py
wellpapp/shell/findtag.py
wellpapp/shell/fsck.py
wellpapp/shell/fusefs.py
wellpapp/shell/implies.py
wellpapp/shell/make_cache.py
wellpapp/shell/mergetags.py
wellpapp/shell/mkalias.py
wellpapp/shell/mktag.py
wellpapp/shell/modtag.py
wellpapp/shell/order.py
wellpapp/shell/replace.py
wellpapp/shell/rmalias.py
wellpapp/shell/rmpost.py
wellpapp/shell/rotate.py
wellpapp/shell/setprop.py
wellpapp/shell/show.py
wellpapp/shell/tag.py
wellpapp/shell/tagwindow.py
wellpapp-2021.2.25.dist-info/LICENSE
wellpapp-2021.2.25.dist-info/METADATA
wellpapp-2021.2.25.dist-info/WHEEL
wellpapp-2021.2.25.dist-info/entry_points.txt
wellpapp-2021.2.25.dist-info/top_level.txt
wellpapp-2021.2.25.dist-info/RECORD
