Metadata-Version: 2.1
Name: wellpapp
Version: 2021.2.25
Summary: Client library and application for the wellpapp image tagging system.
Home-page: https://github.com/drougge/wellpapp-pyclient
Author: Carl Drougge
Author-email: bearded@longhaired.org
License: MIT
Platform: UNKNOWN
Requires-Python: >=2.7, !=3.0.*, !=3.1.*, !=3.2.*, !=3.3.*, !=3.4.*
Requires-Dist: Pillow (>=3.1.2)
Requires-Dist: PyGObject (>=3.20)
Provides-Extra: all
Requires-Dist: fuse-python (>=0.3.1) ; (python_version < "3") and extra == 'all'
Requires-Dist: fuse-python (>=1.0.0) ; (python_version > "3") and extra == 'all'
Provides-Extra: fuse
Requires-Dist: fuse-python (>=0.3.1) ; (python_version < "3") and extra == 'fuse'
Requires-Dist: fuse-python (>=1.0.0) ; (python_version > "3") and extra == 'fuse'
